nimba/__init__.py
nimba/__main__.py
nimba/apps.py
nimba/commands/__init__.py
nimba/commands/base.py
nimba/commands/createapp.py
nimba/core/__init__.py
nimba/core/exceptions.py
nimba/core/server.py
nimba/core/welcom.py
nimba/http/__init__.py
nimba/http/checks.py
nimba/http/cookies.py
nimba/http/errors.py
nimba/http/request.py
nimba/http/resolver.py
nimba/http/response.py
nimba/http/utils.py
nimba/middleware/__init__.py
nimba/staticfiles/nimba/main.css
nimba/staticfiles/nimba/img/nimba-logo.png
nimba/staticfiles/nimba/img/nimba.ico
nimba/templates/nimba/errors/401.html
nimba/templates/nimba/errors/404.html
nimba/templates/nimba/errors/500.html
nimba/test/__init__.py
nimba/test/client.py
tests/__init__.py
tests/__init__.pyc
tests/__main__.py
tests/test_application.py
tests/test_command.py
tests/test_loader.py
tests/test_router.py
tests/__pycache__/__init__.cpython-38.pyc
tests/__pycache__/__main__.cpython-38.pyc
tests/__pycache__/test_application.cpython-38-pytest-6.2.4.pyc
tests/__pycache__/test_application.cpython-38.pyc
tests/__pycache__/test_command.cpython-38-pytest-6.2.4.pyc
tests/__pycache__/test_command.cpython-38.pyc
tests/__pycache__/test_loader.cpython-38-pytest-6.2.4.pyc
tests/__pycache__/test_loader.cpython-38.pyc
tests/__pycache__/test_router.cpython-38-pytest-6.2.4.pyc
tests/__pycache__/test_router.cpython-38.pyc
nimba-0.0.14.dist-info/LICENSE
nimba-0.0.14.dist-info/METADATA
nimba-0.0.14.dist-info/WHEEL
nimba-0.0.14.dist-info/entry_points.txt
nimba-0.0.14.dist-info/top_level.txt
nimba-0.0.14.dist-info/RECORD
