Metadata-Version: 2.1
Name: nimba
Version: 0.0.14
Summary: Nimba is a python web framework for lazy developers, focusing only on your needs.
Home-page: https://github.com/hadpro24/nimba-framework
Author: Harouna Diallo
Author-email: dev.harouna@gmail.com
License: BSD-3-Clause
Project-URL: Documentation, https://docs.nimbasolution.com/
Project-URL: Release notes, https://docs.nimbasolution.com/stable/releases/
Project-URL: Source, https://github.com/hadpro24/nimba-framework
Keywords: python,python3,framework,nimba,nimba-solution,web
Platform: UNKNOWN
Classifier: Development Status :: 4 - Beta
Classifier: Environment :: Web Environment
Classifier: Intended Audience :: Developers
Classifier: License :: OSI Approved :: BSD License
Classifier: Operating System :: OS Independent
Classifier: Programming Language :: Python
Classifier: Programming Language :: Python :: 3
Classifier: Programming Language :: Python :: 3 :: Only
Classifier: Programming Language :: Python :: 3.6
Classifier: Programming Language :: Python :: 3.7
Classifier: Programming Language :: Python :: 3.8
Classifier: Topic :: Internet :: WWW/HTTP
Classifier: Topic :: Internet :: WWW/HTTP :: Dynamic Content
Classifier: Topic :: Internet :: WWW/HTTP :: WSGI
Classifier: Topic :: Software Development :: Libraries :: Application Frameworks
Classifier: Topic :: Software Development :: Libraries :: Python Modules
Requires-Python: >=3.6
License-File: LICENSE
